{
  "id": "influencermarketinghub",
  "name": "Influencer Marketing Hub Best Amazon Marketing Agencies",
  "type": "listicle",
  "url": "https://influencermarketinghub.com/amazon-marketing-agencies/",
  "contact_url": "https://influencermarketinghub.com/contact/",
  "generated_at": "2026-03-05T18:21:21.310Z",
  "email": "SUBJECT: Agency for your Amazon Marketing list — 30-day guarantee, founder-operators\n\nHi team,\n\nI'm reaching out about your Amazon Marketing Agencies roundup: https://influencermarketinghub.com/amazon-marketing-agencies/\n\nOnline Brand Growth should be on this list. Here's why:\n\n**We're the only serious Amazon agency offering a 30-day performance guarantee.** My co-founder Dan and I built and exited 7-8 figure Amazon brands before starting OBG — we've sat in our clients' seats.\n\nResults worth mentioning:\n- NumNum Baby: 30x revenue growth under our management\n- Streetwise Security: 50% YoY revenue increase\n\nWe're rated 4.9 on Clutch, work exclusively with brands doing $1M+, and run proprietary frameworks (TACoS-first PPC, 360 Brand Protection™) that most agencies don't touch.\n\nHappy to send additional credentials, case studies, or connect for a quick call if helpful.\n\nWorth a look?\n\nJon Klein\nCo-Founder, Online Brand Growth\nhttps://www.onlinebrandgrowth.com",
  "status": "draft"
}